tekkare_dev_kit/__init__.py
tekkare_dev_kit/database_manager/README.md
tekkare_dev_kit/database_manager/__init__.py
tekkare_dev_kit/database_manager/directus_operator.py
tekkare_dev_kit/database_manager/elasticsearch_operator.py
tekkare_dev_kit/database_manager/gcloud_operator.py
tekkare_dev_kit/database_manager/mview_operator.py
tekkare_dev_kit/database_manager/mysql_operator.py
tekkare_dev_kit/database_manager/oip_api_operator.py
tekkare_dev_kit/database_manager/redshift_operator.py
tekkare_dev_kit/database_manager/s3_operator.py
tekkare_dev_kit/database_manager/snowflake_operator.py
tekkare_dev_kit/dataclass_manager/README.md
tekkare_dev_kit/dataclass_manager/__init__.py
tekkare_dev_kit/dataclass_manager/dictionary.py
tekkare_dev_kit/dataclass_manager/raw_data_file.py
tekkare_dev_kit/decorator_manager/README.md
tekkare_dev_kit/decorator_manager/__init__.py
tekkare_dev_kit/decorator_manager/debug_decorator.py
tekkare_dev_kit/decorator_manager/functional_decorator.py
tekkare_dev_kit/file_manager/README.md
tekkare_dev_kit/file_manager/__init__.py
tekkare_dev_kit/file_manager/file_as_bytes.py
tekkare_dev_kit/file_manager/file_detector.py
tekkare_dev_kit/file_manager/file_downloader.py
tekkare_dev_kit/file_manager/file_operator.py
tekkare_dev_kit/file_manager/file_writer.py
tekkare_dev_kit/pandas_manager/README.md
tekkare_dev_kit/pandas_manager/__init__.py
tekkare_dev_kit/pandas_manager/checker.py
tekkare_dev_kit/pandas_manager/detector.py
tekkare_dev_kit/pandas_manager/io.py
tekkare_dev_kit/pandas_manager/manipulator.py
tekkare_dev_kit/pandas_manager/normalizer.py
tekkare_dev_kit/sql_utils/__init__.py
tekkare_dev_kit/sql_utils/sql2sf.py
tekkare_dev_kit/sql_utils/v_generate_tbl_ddl.sql
tekkare_dev_kit/verification_utils/__init__.py
tekkare_dev_kit/verification_utils/verifification.py
tekkare_dev_kit-2.4.0.dist-info/LICENSE
tekkare_dev_kit-2.4.0.dist-info/METADATA
tekkare_dev_kit-2.4.0.dist-info/WHEEL
tekkare_dev_kit-2.4.0.dist-info/RECORD
