Metadata-Version: 2.1
Name: tekkare-dev-kit
Version: 2.4.0
Summary: Interact with OIP ecosystem.
Home-page: https://github.com/Tekkare/rcd-dev-kit
License: MIT
Author: Maxime KIEFFER
Requires-Python: >=3.9,<4.0
Classifier: Intended Audience :: Developers
Classifier: License :: OSI Approved :: MIT License
Classifier: Programming Language :: Python :: 3
Classifier: Programming Language :: Python :: 3.9
Classifier: Programming Language :: Python :: 3.10
Classifier: Programming Language :: Python :: 3.11
Classifier: Programming Language :: Python :: 3.12
Classifier: Programming Language :: Python :: 3.8
Classifier: Topic :: Software Development :: Build Tools
Provides-Extra: ctx
Provides-Extra: docs
Provides-Extra: google
Provides-Extra: py-test
Requires-Dist: Sphinx (>=7.2.6,<8.0.0) ; extra == "docs"
Requires-Dist: boto3 (>=1.28.12,<2.0.0)
Requires-Dist: botocore (>=1.31.12,<2.0.0)
Requires-Dist: connectorx (>=0.3.2,<0.4.0) ; extra == "ctx"
Requires-Dist: elasticsearch (>=8.8.2,<9.0.0)
Requires-Dist: google (>=3.0.0,<4.0.0) ; extra == "google"
Requires-Dist: google-api-python-client (>=2.47.0,<3.0.0) ; extra == "google"
Requires-Dist: google-cloud (>=0.34.0,<0.35.0)
Requires-Dist: google-cloud-storage (>=2.3.0,<3.0.0) ; extra == "google"
Requires-Dist: llama-index-embeddings-huggingface (>=0.1.4,<0.2.0)
Requires-Dist: llama-index-readers-elasticsearch (>=0.1.3,<0.2.0)
Requires-Dist: llama-index-vector-stores-elasticsearch (>=0.1.5,<0.2.0)
Requires-Dist: myst-parser (>=2.0.0,<3.0.0) ; extra == "docs"
Requires-Dist: numpy (>=1.25.1,<2.0.0)
Requires-Dist: pandas (>=2.0.3,<3.0.0)
Requires-Dist: psycopg2-binary (>=2.9.6,<3.0.0)
Requires-Dist: py-markdown-table (>=0.4.0,<0.5.0)
Requires-Dist: pytest (>=7.4.0,<8.0.0) ; extra == "py-test"
Requires-Dist: pytest-cov (>=4.1.0,<5.0.0) ; extra == "py-test"
Requires-Dist: python-dotenv (>=1.0.0,<2.0.0)
Requires-Dist: scikit-learn (>=1.3.0,<2.0.0)
Requires-Dist: snowflake-connector-python[pandas] (>=3.2.1,<4.0.0)
Requires-Dist: sphinx-autoapi (>=3.0.0,<4.0.0) ; extra == "docs"
Requires-Dist: sphinx-rtd-theme (==1.3.0) ; extra == "docs"
Requires-Dist: sphinxcontrib-napoleon (==0.7) ; extra == "docs"
Requires-Dist: sqlalchemy-redshift (>=0.8.14,<0.9.0)
Requires-Dist: sqlparse (>=0.4.4,<0.5.0)
Requires-Dist: statsmodels (>=0.14.0,<0.15.0)
Requires-Dist: tqdm (>=4.65.0,<5.0.0)
Requires-Dist: twine (>=5.0.0,<6.0.0)
Project-URL: Repository, https://github.com/Tekkare/rcd-dev-kit
